alibabacloud/__init__.py
alibabacloud/__main__.py
alibabacloud/ecs.py
alibabacloud/oss.py
alibabacloud/rds.py
alibabacloud/slb.py
alibabacloud/vpc.py
alibabacloude-2.13.37.dist-info/licenses/LICENSE
alibabacloude-2.13.37.dist-info/METADATA
alibabacloude-2.13.37.dist-info/WHEEL
alibabacloude-2.13.37.dist-info/entry_points.txt
alibabacloude-2.13.37.dist-info/top_level.txt
alibabacloude-2.13.37.dist-info/RECORD
