Metadata-Version: 2.4
Name: alibabacloude
Version: 2.13.37
Summary: 阿里云Python SDK v2
Home-page: https://github.com/aliyun/alibabacloud-python-sdk-v2
Author: Alibaba Cloud
Author-email: Alibaba Cloud <sdk-team@alibabacloud.com>
License-Expression: MIT
Project-URL: Homepage, https://github.com/aliyun/alibabacloud-python-sdk-v2
Project-URL: Documentation, https://help.aliyun.com/document_detail/101286.html
Project-URL: Repository, https://github.com/aliyun/alibabacloud-python-sdk-v2
Project-URL: Bug Tracker, https://github.com/aliyun/alibabacloud-python-sdk-v2/issues
Keywords: alibaba-cloud,aliyun,sdk,ecs,oss,rds,vpc,slb
Classifier: Development Status :: 4 - Beta
Classifier: Intended Audience :: Developers
Classifier: Programming Language :: Python :: 3
Classifier: Programming Language :: Python :: 3.10
Classifier: Programming Language :: Python :: 3.11
Classifier: Programming Language :: Python :: 3.12
Classifier: Topic :: Internet :: WWW/HTTP
Classifier: Topic :: Software Development :: Libraries :: Python Modules
Classifier: Topic :: System :: Distributed Computing
Requires-Python: >=3.10
License-File: LICENSE
Provides-Extra: dev
Requires-Dist: pytest>=6.0; extra == "dev"
Requires-Dist: black>=21.0; extra == "dev"
Requires-Dist: flake8>=3.8; extra == "dev"
Dynamic: author
Dynamic: home-page
Dynamic: license-file
Dynamic: requires-python
